Metadata-Version: 1.0
Name: databasetools
Version: 0.4.1
Summary: Convenient data storage toolkit.
Home-page: https://github.com/mrstephenneal/databasetools
Author: Stephen Neal
Author-email: stephen@stephenneal.net
License: MIT License
Platform: UNKNOWN
